extract/__init__.py
extract/ga_reporting.py
extract/processor.py
extract/utils/logger.py
bart_extract_ga-0.1.0.dist-info/WHEEL
bart_extract_ga-0.1.0.dist-info/METADATA
bart_extract_ga-0.1.0.dist-info/RECORD
