Metadata-Version: 2.1
Name: bart-extract-ga
Version: 0.1.0
Summary: 
Author: Cesar Augusto
Author-email: cesarabruschetta@gmail.com
Requires-Python: >=3.6.1,<3.7
Classifier: Programming Language :: Python :: 3
Requires-Dist: google-api-python-client (==1.9.1)
Requires-Dist: pandas (>=1.0.4,<2.0.0)
Requires-Dist: pyarrow (>=0.17.1,<0.18.0)
Requires-Dist: s3fs (>=0.4.2,<0.5.0)
